launcher_tool/__init__.py
launcher_tool/__main__.py
launcher_tool/bdist_launcher.py
launcher_tool/copy_launcher.py
launcher_tool/create_python27_minimal.py
launcher_tool/download_python3_minimal.py
launcher_tool/icon.py
launcher_tool/launcher.py
launcher_tool/launcher27-32.exe
launcher_tool/launcher27-64.exe
launcher_tool/launcher3-32.exe
launcher_tool/launcher3-64.exe
launcher_tool/launcher_zip.py
launcher_tool/resource_editor.py
python_embedded_launcher-0.14.dist-info/DESCRIPTION.rst
python_embedded_launcher-0.14.dist-info/METADATA
python_embedded_launcher-0.14.dist-info/RECORD
python_embedded_launcher-0.14.dist-info/WHEEL
python_embedded_launcher-0.14.dist-info/entry_points.txt
python_embedded_launcher-0.14.dist-info/metadata.json
python_embedded_launcher-0.14.dist-info/top_level.txt
